getdep/__init__.py
getdep/getdep.py
getdep/utility.py
getdep-1.2.1.dist-info/METADATA
getdep-1.2.1.dist-info/WHEEL
getdep-1.2.1.dist-info/top_level.txt
getdep-1.2.1.dist-info/RECORD
