Metadata-Version: 2.1
Name: getdep
Version: 1.2.1
Summary: Get dependencies for a given package management system and a given package
Home-page: https://github.com/remiflavien1/getdep
Author: shadawck
Author-email: hug211mire@gmail.com
License: MIT
Keywords: security,dependencies,package management,dependencies manager,composer,yarn,apt,chocolatey,nuget
Platform: UNKNOWN
Classifier: License :: OSI Approved :: MIT License
Classifier: Programming Language :: Python :: 3
Classifier: Programming Language :: Python :: 3.7
Classifier: Topic :: Security
Requires-Dist: requests
Provides-Extra: test
Requires-Dist: pytest ; extra == 'test'
Requires-Dist: pytest-cov ; extra == 'test'
